setup.py
crog/__init__.py
crog/crog.py
crog.egg-info/PKG-INFO
crog.egg-info/SOURCES.txt
crog.egg-info/dependency_links.txt
crog.egg-info/top_level.txt