Metadata-Version: 1.1
Name: crog
Version: 0.0.2
Summary: Generate cronjobs for python script
Home-page: http://github.com/herrersystem/crog
Author: herrersystem
Author-email: anton.millescamps@evhunter.fr
License: GNU General Public License (GPL)
Keywords: crog cron cronjob
Platform: UNKNOWN
Classifier: Development Status :: 4 - Beta
Classifier: Intended Audience :: Developers
Classifier: License :: OSI Approved :: GNU General Public License (GPL)
Classifier: Topic :: Software Development
Classifier: Topic :: Software Development :: Libraries
Classifier: Programming Language :: Python
Classifier: Programming Language :: Python :: 3
Classifier: Programming Language :: Python :: 3.4
Classifier: Programming Language :: Python :: 3.5
